build/lib/build/lib/build/lib/build/lib/build/lib/build/lib/mr_scraper/api/__init__.py
build/lib/build/lib/build/lib/build/lib/build/lib/build/lib/mr_scraper/api/models.py
build/lib/build/lib/build/lib/build/lib/build/lib/build/lib/mr_scraper/api/transforms.py
build/lib/build/lib/build/lib/build/lib/build/lib/mr_scraper/api/__init__.py
build/lib/build/lib/build/lib/build/lib/build/lib/mr_scraper/api/models.py
build/lib/build/lib/build/lib/build/lib/build/lib/mr_scraper/api/transforms.py
build/lib/build/lib/build/lib/build/lib/mr_scraper/api/__init__.py
build/lib/build/lib/build/lib/build/lib/mr_scraper/api/models.py
build/lib/build/lib/build/lib/build/lib/mr_scraper/api/transforms.py
build/lib/build/lib/build/lib/mr_scraper/api/__init__.py
build/lib/build/lib/build/lib/mr_scraper/api/models.py
build/lib/build/lib/build/lib/mr_scraper/api/transforms.py
build/lib/build/lib/mr_scraper/api/__init__.py
build/lib/build/lib/mr_scraper/api/models.py
build/lib/build/lib/mr_scraper/api/transforms.py
build/lib/mr_scraper/api/__init__.py
build/lib/mr_scraper/api/models.py
build/lib/mr_scraper/api/transforms.py
mr_scraper/api/__init__.py
mr_scraper/api/models.py
mr_scraper/api/transforms.py
mr_scraper-0.8.0.dist-info/LICENSE
mr_scraper-0.8.0.dist-info/METADATA
mr_scraper-0.8.0.dist-info/WHEEL
mr_scraper-0.8.0.dist-info/top_level.txt
mr_scraper-0.8.0.dist-info/RECORD
