Metadata-Version: 2.1
Name: mr-scraper
Version: 0.8.0
Summary: Library to create scrapers in python
Home-page: UNKNOWN
Author: fernandojerez
License: Apache
Platform: UNKNOWN
Requires: webpilot
Requires: requests
License-File: LICENSE
Requires-Dist: webpilot
Requires-Dist: requests
